fmp_api_client/__init__.py
fmp_api_client/analyst.py
fmp_api_client/base.py
fmp_api_client/calendar.py
fmp_api_client/client.py
fmp_api_client/company.py
fmp_api_client/const.py
fmp_api_client/directory.py
fmp_api_client/discounted_cashflow.py
fmp_api_client/economics.py
fmp_api_client/indexes.py
fmp_api_client/insider_trades.py
fmp_api_client/market_hours.py
fmp_api_client/market_performance.py
fmp_api_client/news.py
fmp_api_client/plan.py
fmp_api_client/quote.py
fmp_api_client/search.py
fmp_api_client/statements.py
fmp_api_client-0.0.1.dist-info/LICENSE
fmp_api_client-0.0.1.dist-info/METADATA
fmp_api_client-0.0.1.dist-info/WHEEL
fmp_api_client-0.0.1.dist-info/RECORD
